Flask_Vue_Scaffold-0.1.1.dist-info/DESCRIPTION.rst
Flask_Vue_Scaffold-0.1.1.dist-info/METADATA
Flask_Vue_Scaffold-0.1.1.dist-info/RECORD
Flask_Vue_Scaffold-0.1.1.dist-info/WHEEL
Flask_Vue_Scaffold-0.1.1.dist-info/entry_points.txt
Flask_Vue_Scaffold-0.1.1.dist-info/metadata.json
Flask_Vue_Scaffold-0.1.1.dist-info/top_level.txt
flask_vue_scaffold/__init__.py
flask_vue_scaffold/cli.py
flask_vue_scaffold/data/.babelrc
flask_vue_scaffold/data/.editorconfig
flask_vue_scaffold/data/.eslintignore
flask_vue_scaffold/data/.eslintrc.js
flask_vue_scaffold/data/.gitignore
flask_vue_scaffold/data/.postcssrc.js
flask_vue_scaffold/data/README.md.tpl
flask_vue_scaffold/data/index.html.tpl
flask_vue_scaffold/data/package.json.tpl
flask_vue_scaffold/data/setup.py.tpl
flask_vue_scaffold/data/yarn.lock
flask_vue_scaffold/data/bin/devserver
flask_vue_scaffold/data/build/build.js
flask_vue_scaffold/data/build/check-versions.js
flask_vue_scaffold/data/build/dev-client.js
flask_vue_scaffold/data/build/dev-server.js
flask_vue_scaffold/data/build/utils.js
flask_vue_scaffold/data/build/vue-loader.conf.js
flask_vue_scaffold/data/build/webpack.base.conf.js
flask_vue_scaffold/data/build/webpack.dev.conf.js
flask_vue_scaffold/data/build/webpack.prod.conf.js
flask_vue_scaffold/data/build/webpack.test.conf.js
flask_vue_scaffold/data/config/dev.env.js
flask_vue_scaffold/data/config/index.js.tpl
flask_vue_scaffold/data/config/prod.env.js
flask_vue_scaffold/data/config/test.env.js
flask_vue_scaffold/data/pyapp/__init__.py
flask_vue_scaffold/data/pyapp/app.py
flask_vue_scaffold/data/pyapp/api/__init__.py
flask_vue_scaffold/data/pyapp/cli/__init__.py.tpl
flask_vue_scaffold/data/pyapp/cli/base.py.tpl
flask_vue_scaffold/data/pyapp/cli/devserver.py.tpl
flask_vue_scaffold/data/pyapp/templates/index.html.tpl
flask_vue_scaffold/data/src/App.vue
flask_vue_scaffold/data/src/main.js
flask_vue_scaffold/data/src/assets/Flask-logo.png
flask_vue_scaffold/data/src/assets/logo.png
flask_vue_scaffold/data/src/components/HelloWorld.vue
flask_vue_scaffold/data/src/router/index.js
flask_vue_scaffold/data/src/store/index.js
flask_vue_scaffold/data/src/store/modules/example.js
flask_vue_scaffold/data/test/e2e/nightwatch.conf.js
flask_vue_scaffold/data/test/e2e/runner.js
