Metadata-Version: 2.0
Name: Flask-Vue-Scaffold
Version: 0.1.1
Summary: Create a Flask+Vue.js app in seconds.
Home-page: https://github.com/treebee/flask-vue-scaffold
Author: Patrick Muehlbauer
Author-email: patrick@opentrash.org
License: UNKNOWN
Platform: UNKNOWN
Classifier: License :: OSI Approved :: Apache Software License
Classifier: Programming Language :: Python :: 3.6
Requires-Dist: click
